{
	"nav":[{
		"title":"篮球",
		"href":"javascript:;"
	},{
		"title":"跑步",
		"href":"javascript:;"
	},{
		"title":"综训",
		"href":"javascript:;"
	},{
		"title":"户外训练",
		"href":"javascript:;"
	},{
		"title":"配件",
		"href":"javascript:;"
	},{
		"title":"团购",
		"href":"javascript:;"
	}],
	"dl":[{
		"dt":"鞋",
		"dd":[
		      "篮球鞋",
		      "儿童篮球鞋"
		      ]
	},{
		"dt":"服",
		"dd":[
		      "比赛服",
		      "篮球服",
		      "篮球裤"
		      ]
	},{
		"dt":"科技",
		"dd":[
		      "弹力胶",
		      "耐磨橡胶",
		      "气垫科技",
		      "耐磨防臭"
		      ]
	},{
		"dt":"系列",
		"dd":[
		      "霸道",
		      "水泥克星",
		      "kg",
		      "隆多"
		      ]
	}]
}
